[
    {
        "ranks": [
            "Banners1"
        ],
        "users": [
            "-Jane Doe",
            "-Yggdrasil",
            "AG TrinalGore54",
            "ALISSVR",
            "Aeris_Kami",
            "Amurysse",
            "AwesomeBayou26",
            "BebecitaShey",
            "CapibaraвА§ 1eb1",
            "CopycatPortal",
            "Cuervito_",
            "Danny_504",
            "Diegomex 8f11",
            "DбіА П…™",
            "Erika01",
            "FXSCAR",
            "Faaka_vr",
            "Farra_v18",
            "Fire_Starter",
            "Fluffy_kiwi",
            "FryslangX",
            "Funas",
            "GreyGrace",
            "INFINITY_II",
            "Icќњn4500",
            "Jensell1",
            "John Wipe",
            "JokerStein",
            "Josuewe",
            "K I Z T A S",
            "KaosKynG",
            "Karlozz",
            "KirikuVT",
            "Lady Farya",
            "LadyBoom9",
            "LiardT",
            "Luismi92",
            "Mike300w",
            "MithZh",
            "MokaPaut",
            "Naim Ulloa",
            "Nanadelka",
            "Pao_EliUwu19k",
            "ParzivalOkazaki",
            "Pely Vega",
            "Prototipo0121",
            "Robi1",
            "RocketSaul",
            "SCrifer",
            "SSJSour",
            "Sanssha",
            "Shyvanae",
            "SrCuatro",
            "SugarLoliUwU",
            "SwuuXy",
            "SymphonyOwU",
            "S‘ЛѕЕ…≥“љ",
            "Tocina Bacon",
            "VE–ЯDE∆ђ∆ђќЫ",
            "VenusAlyx",
            "Vexiop",
            "Warm¬Ѓ",
            "XionWolf V",
            "XmatrixX97",
            "Yamita",
            "Yasashi Teyko",
            "Yukќє-Nќ±gќ±to",
            "YuuCaliente19¬∞",
            "ZeroPositivo",
            "ZooboxSan",
            "ariвА§33",
            "berna mow",
            "biliustick48",
            "christech",
            "hakunamatata93",
            "hugoz05",
            "iTeo_zz",
            "innari",
            "inniedum",
            "kar—Г",
            "kfezito",
            "lordbelcebu",
            "madisonlu98",
            "marovimartin",
            "s Я П ¬Ѓ",
            "ucranianalive_",
            "∆ШѕЕ—Х—В",
            " А К Д К Я",
            " Ъ -Moonwolf- …Ю",
            " Ъ-Aquileswolf-…Ю",
            " ЪЋЪ ЋПЋЛпЉґпЉ©пЉ≤пЉµпЉ≥ЋКЋО ЋЪ…Ю",
            "ЋЪ Ъ sбіЫбіА А …ЮЋЪ",
            "бГ¶Komisito",
            "біЛ…™біЕбіА_ Я Пs22",
            "біН…™…ібіЫ Є",
            "біЬ—ХбіА…Ґ…™бі† А",
            "гАОѕЯsxѕЯгАПгГД",
            "пЉҐпљПпљМпљМпљЙпљФпљП гВє",
            "пЉ≥пљИпљОпљБпљРпљЙпљЙ"
        ],
        "groups": [
            "Banners1"
        ],
        "custom_indexes": {
            "13": [
                "FXSCAR",
                "XionWolf V",
                "MokaPaut",
                "GreyGrace",
                "Naim Ulloa",
                "KirikuVT",
                "RocketSaul",
                "Cuervito_",
                "Lady Farya",
                "-Yggdrasil",
                "Yamita"
            ],
            "16": [
                "kar—Г",
                "JokerStein"
            ],
            "4": [
                "∆ШѕЕ—Х—В",
                "Warm¬Ѓ",
                " ЪЋЪ ЋПЋЛпЉґпЉ©пЉ≤пЉµпЉ≥ЋКЋО ЋЪ…Ю",
                "ParzivalOkazaki"
            ],
            "11": [
                "Amurysse"
            ],
            "15": [
                "VenusAlyx",
                "Faaka_vr",
                "s Я П ¬Ѓ",
                "kfezito",
                "ЋЪ Ъ sбіЫбіА А …ЮЋЪ"
            ],
            "3": [
                "Yukќє-Nќ±gќ±to"
            ],
            "5": [
                "MithZh",
                "бГ¶Komisito",
                "Funas"
            ],
            "2": [
                "біН…™…ібіЫ Є",
                "XmatrixX97",
                "гАОѕЯsxѕЯгАПгГД",
                "biliustick48",
                "Nanadelka",
                "K I Z T A S",
                "Prototipo0121",
                "John Wipe",
                "SugarLoliUwU",
                "CopycatPortal",
                "Diegomex 8f11",
                "Icќњn4500",
                "AG TrinalGore54",
                "inniedum",
                "VE–ЯDE∆ђ∆ђќЫ",
                "KaosKynG",
                "YuuCaliente19¬∞",
                "Sanssha",
                "біЛ…™біЕбіА_ Я Пs22",
                " А К Д К Я",
                "DбіА П…™",
                " Ъ-Aquileswolf-…Ю",
                " Ъ -Moonwolf- …Ю",
                "berna mow",
                "BebecitaShey",
                "ucranianalive_",
                "ZeroPositivo",
                "marovimartin",
                "LadyBoom9",
                "Josuewe",
                "Erika01",
                "SCrifer",
                "Luismi92",
                "SrCuatro",
                "hakunamatata93",
                "Aeris_Kami",
                "iTeo_zz",
                "-Jane Doe",
                "CapibaraвА§ 1eb1",
                "Tocina Bacon",
                "Robi1",
                "Fire_Starter",
                "SSJSour",
                "LiardT",
                "Mike300w",
                "SwuuXy",
                "S‘ЛѕЕ…≥“љ",
                "Danny_504",
                "lordbelcebu",
                "Pao_EliUwu19k",
                "Farra_v18",
                "FryslangX",
                "madisonlu98",
                "INFINITY_II",
                "AwesomeBayou26",
                "hugoz05",
                "Yasashi Teyko",
                "ALISSVR",
                "ZooboxSan",
                "Shyvanae",
                "Karlozz"
            ],
            "6": [
                "біЬ—ХбіА…Ґ…™бі† А",
                "innari",
                "пЉ≥пљИпљОпљБпљРпљЙпљЙ",
                "Jensell1",
                "Fluffy_kiwi",
                "SymphonyOwU",
                "Pely Vega",
                "ariвА§33",
                "christech",
                "Vexiop",
                "пЉҐпљПпљМпљМпљЙпљФпљП гВє"
            ]
        }
    },
    {
        "ranks": [
            "Banners2"
        ],
        "users": [
            "Akita NeruгАЖ",
            "D O V ƒТ",
            "Dios Carmesi",
            "D…™біЗ A…ібіП…і ПбіН…™біЫбіАћИбіЫ",
            "ErillвА§вЩ•",
            "Gio¬©",
            "JMAUPS",
            "JanusRR",
            "KatheKatt",
            "Kii70",
            "MarlonQC",
            "MaurixG",
            "MќЫTHIќЫ",
            "OsitoPauPau",
            "ReikaVermysthra",
            "Roxytooty",
            "SRHiggins",
            "Sainthe",
            "Seruly",
            "Shirou1711",
            "StreetLove?",
            "Tatsumi02233",
            "Viz1c0l",
            "aaronquito",
            "dequer12",
            "duckis",
            "josyelin",
            "oyasuu_2213",
            "pepemota7749",
            "sara_dj03",
            "wtf_nin4",
            "¬∞ChimiRuMyX¬∞",
            "…™біЫбіҐбіЬ…і П ¬Ѓ",
            " Ъ…Ю sбіЗx біЕбіЗs…™ АбіЗ",
            "бГЭ Y A M I бГЭ",
            "бГ¶EquiбГ¶",
            "бГ¶біЛбіАбіН…™біН…™",
            "біДћґ ЬћґбіАћґ…іћґбіЗћґ Яћґ",
            "біЗбіЫбіАбіЕ…™ ЯбіАбі†",
            "біЛ…™біЛo",
            "біПnly",
            "біШбіАбіШ…™біА…ібіЕ ПбіЛ…™…і…Ґ¬Ѓ",
            "бі∞біЉеНДбіђ",
            "пЉіпЉѓпЉЂпЉ°пЉєпЉѓ",
            "пљНпљЕпљПпљЧ?"
        ],
        "groups": [
            "Banners2"
        ],
        "custom_indexes": {
            "14": [
                "MarlonQC"
            ],
            "4": [
                "Shirou1711",
                "Roxytooty",
                "OsitoPauPau",
                "Gio¬©",
                "бГ¶біЛбіАбіН…™біН…™",
                "ErillвА§вЩ•",
                "пљНпљЕпљПпљЧ?",
                "бГ¶EquiбГ¶",
                "Seruly",
                "D O V ƒТ",
                "MaurixG",
                " Ъ…Ю sбіЗx біЕбіЗs…™ АбіЗ",
                "ReikaVermysthra",
                "бі∞біЉеНДбіђ",
                "біШбіАбіШ…™біА…ібіЕ ПбіЛ…™…і…Ґ¬Ѓ"
            ],
            "2": [
                "sara_dj03"
            ],
            "12": [
                "біЗбіЫбіАбіЕ…™ ЯбіАбі†",
                "…™біЫбіҐбіЬ…і П ¬Ѓ",
                "StreetLove?",
                "Kii70",
                "біДћґ ЬћґбіАћґ…іћґбіЗћґ Яћґ",
                "біЛ…™біЛo",
                "біПnly"
            ],
            "7": [
                "KatheKatt"
            ],
            "13": [
                "SRHiggins",
                "D…™біЗ A…ібіП…і ПбіН…™біЫбіАћИбіЫ",
                "oyasuu_2213",
                "Tatsumi02233",
                "JMAUPS",
                "MќЫTHIќЫ",
                "JanusRR"
            ],
            "6": [
                "Dios Carmesi"
            ],
            "1": [
                "Akita NeruгАЖ",
                "josyelin",
                "dequer12",
                "Sainthe"
            ],
            "11": [
                "пЉіпЉѓпЉЂпЉ°пЉєпЉѓ",
                "duckis",
                "бГЭ Y A M I бГЭ"
            ],
            "15": [
                "pepemota7749",
                "aaronquito",
                "wtf_nin4",
                "¬∞ChimiRuMyX¬∞",
                "Viz1c0l"
            ]
        }
    },
    {
        "ranks": [
            "InversorC"
        ],
        "users": [
            "NeoDino"
        ],
        "groups": [
            "InversorC"
        ]
    },
    {
        "ranks": [
            "JokerCircus"
        ],
        "users": [
            "-Yggdrasil",
            "Cuervito_",
            "FXSCAR",
            "GreyGrace",
            "KirikuVT",
            "Lady Farya",
            "MarlonQC",
            "MokaPaut",
            "Naim Ulloa",
            "RocketSaul",
            "XionWolf V",
            "Yamita"
        ],
        "groups": [
            "JokerCircus"
        ]
    },
    {
        "ranks": [
            "Mod"
        ],
        "users": [
            "MarlonQC",
            "ParzivalOkazaki",
            "Warm¬Ѓ",
            "∆ШѕЕ—Х—В",
            " ЪЋЪ ЋПЋЛпЉґпЉ©пЉ≤пЉµпЉ≥ЋКЋО ЋЪ…Ю"
        ],
        "groups": [
            "Mod"
        ]
    },
    {
        "ranks": [
            "DancerCari"
        ],
        "users": [
            "D O V ƒТ",
            "ErillвА§вЩ•",
            "OsitoPauPau",
            "ReikaVermysthra",
            "Roxytooty",
            "Seruly",
            "Shirou1711",
            " Ъ…Ю sбіЗx біЕбіЗs…™ АбіЗ",
            "бГ¶EquiбГ¶",
            "бГ¶біЛбіАбіН…™біН…™",
            "біШбіАбіШ…™біА…ібіЕ ПбіЛ…™…і…Ґ¬Ѓ",
            "бі∞біЉеНДбіђ",
            "пљНпљЕпљПпљЧ?"
        ],
        "groups": [
            "DancerCari"
        ]
    },
    {
        "ranks": [
            "DancerGuest"
        ],
        "users": [
            "Faaka_vr",
            "Gio¬©",
            "MaurixG",
            "Mikama",
            "VenusAlyx",
            "kfezito",
            "s Я П ¬Ѓ",
            "≈¶…≠аЄД–ЇаЄД_02",
            "ЋЪ Ъ sбіЫбіА А …ЮЋЪ"
        ],
        "groups": [
            "DancerGuest"
        ]
    },
    {
        "ranks": [
            "Icon"
        ],
        "users": [
            "JokerStein",
            "kar—Г"
        ],
        "groups": [
            "Icon"
        ]
    },
    {
        "ranks": [
            "Bonice"
        ],
        "users": [
            "sara_dj03"
        ],
        "groups": [
            "Bonice"
        ]
    },
    {
        "ranks": [
            "InversorB"
        ],
        "users": [
            "біЗбіЫбіАбіЕ…™ ЯбіАбі†"
        ],
        "groups": [
            "InversorB"
        ]
    },
    {
        "ranks": [
            "DancerCapitan"
        ],
        "users": [
            "Amurysse",
            "KatheKatt"
        ],
        "groups": [
            "DancerCapitan"
        ]
    },
    {
        "ranks": [
            "InversorA"
        ],
        "users": [
            "Dulcec–Њmocandy",
            "D…™біЗ A…ібіП…і ПбіН…™біЫбіАћИбіЫ",
            "Funas",
            "JMAUPS",
            "JanusRR",
            "MithZh",
            "MќЫTHIќЫ",
            "SRHiggins",
            "Tatsumi02233",
            "oyasuu_2213",
            "бГ¶Komisito"
        ],
        "groups": [
            "InversorA"
        ]
    },
    {
        "ranks": [
            "Co-Owner"
        ],
        "users": [
            "Dios Carmesi",
            "Yukќє-Nќ±gќ±to"
        ],
        "groups": [
            "Co-Owner"
        ]
    },
    {
        "ranks": [
            "AdminManager"
        ],
        "users": [
            "Saaa"
        ],
        "groups": [
            "AdminManager"
        ]
    },
    {
        "ranks": [
            "Friends"
        ],
        "users": [
            "K I Z T A S",
            "Nanadelka",
            "XmatrixX97",
            "biliustick48",
            "біН…™…ібіЫ Є",
            "гАОѕЯsxѕЯгАПгГД"
        ],
        "groups": [
            "Friends"
        ]
    },
    {
        "ranks": [
            "VIP"
        ],
        "users": [
            "-Jane Doe",
            "AG TrinalGore54",
            "ALISSVR",
            "Aeris_Kami",
            "Akita NeruгАЖ",
            "AwesomeBayou26",
            "BebecitaShey",
            "CapibaraвА§ 1eb1",
            "CopycatPortal",
            "Danny_504",
            "Diegomex 8f11",
            "DбіА П…™",
            "Erika01",
            "Farra_v18",
            "Fire_Starter",
            "FryslangX",
            "INFINITY_II",
            "Icќњn4500",
            "John Wipe",
            "Josuewe",
            "KaosKynG",
            "Karlozz",
            "Kii70",
            "LadyBoom9",
            "LiardT",
            "Luismi92",
            "Mike300w",
            "Pao_EliUwu19k",
            "Prototipo0121",
            "Robi1",
            "SCrifer",
            "SSJSour",
            "Sainthe",
            "Sanssha",
            "Shyvanae",
            "SrCuatro",
            "StreetLove?",
            "SugarLoliUwU",
            "SwuuXy",
            "S‘ЛѕЕ…≥“љ",
            "Tocina Bacon",
            "VE–ЯDE∆ђ∆ђќЫ",
            "Yasashi Teyko",
            "YuuCaliente19¬∞",
            "ZeroPositivo",
            "ZooboxSan",
            "berna mow",
            "dequer12",
            "duckis",
            "hakunamatata93",
            "hugoz05",
            "iTeo_zz",
            "inniedum",
            "josyelin",
            "lordbelcebu",
            "madisonlu98",
            "marovimartin",
            "ucranianalive_",
            "…™біЫбіҐбіЬ…і П ¬Ѓ",
            " А К Д К Я",
            " Ъ -Moonwolf- …Ю",
            " Ъ-Aquileswolf-…Ю",
            "бГЭ Y A M I бГЭ",
            "біДћґ ЬћґбіАћґ…іћґбіЗћґ Яћґ",
            "біЛ…™біЕбіА_ Я Пs22",
            "біЛ…™біЛo",
            "біПnly",
            "пЉіпЉѓпЉЂпЉ°пЉєпЉѓ"
        ],
        "groups": [
            "VIP"
        ]
    },
    {
        "ranks": [
            "Partner"
        ],
        "users": [
            "Fluffy_kiwi",
            "Jensell1",
            "Pely Vega",
            "SymphonyOwU",
            "Vexiop",
            "Viz1c0l",
            "aaronquito",
            "ariвА§33",
            "christech",
            "innari",
            "pepemota7749",
            "wtf_nin4",
            "¬∞ChimiRuMyX¬∞",
            "біЬ—ХбіА…Ґ…™бі† А",
            "пЉҐпљПпљМпљМпљЙпљФпљП гВє",
            "пЉ≥пљИпљОпљБпљРпљЙпљЙ"
        ],
        "groups": [
            "Partner"
        ]
    }
]